meaningful_re/__init__.py
meaningful_re/expression.py
meaningful_re/meaningful_re.py
meaningful_re-0.1.24.dist-info/LICENSE
meaningful_re-0.1.24.dist-info/METADATA
meaningful_re-0.1.24.dist-info/WHEEL
meaningful_re-0.1.24.dist-info/top_level.txt
meaningful_re-0.1.24.dist-info/RECORD
