Metadata-Version: 2.1
Name: meaningful-re
Version: 0.1.24
Summary: Regular expression builder with chainable methods.
Home-page: https://github.com/aelt/meaningful_re
Author: Alver Lopez
Author-email: alverelt@gmail.com
License: MIT
Platform: UNKNOWN
Classifier: Development Status :: 4 - Beta
Classifier: Intended Audience :: Developers
Classifier: License :: OSI Approved :: MIT License
Classifier: Programming Language :: Python :: 3
